trytond/modules/health_dentistry/COPYING
trytond/modules/health_dentistry/README.rst
trytond/modules/health_dentistry/__init__.py
trytond/modules/health_dentistry/data/dentistry_procedures.xml
trytond/modules/health_dentistry/health_dentistry.py
trytond/modules/health_dentistry/health_dentistry_report.xml
trytond/modules/health_dentistry/health_dentistry_view.xml
trytond/modules/health_dentistry/icons/dentistry.svg
trytond/modules/health_dentistry/locale/ar.po
trytond/modules/health_dentistry/locale/de.po
trytond/modules/health_dentistry/locale/el.po
trytond/modules/health_dentistry/locale/eo.po
trytond/modules/health_dentistry/locale/es.po
trytond/modules/health_dentistry/locale/fr.po
trytond/modules/health_dentistry/locale/health_dentistry.pot
trytond/modules/health_dentistry/locale/it_IT.po
trytond/modules/health_dentistry/locale/ja_JP.po
trytond/modules/health_dentistry/locale/ka.po
trytond/modules/health_dentistry/locale/lo.po
trytond/modules/health_dentistry/locale/pt_BR.po
trytond/modules/health_dentistry/locale/sv.po
trytond/modules/health_dentistry/locale/tr.po
trytond/modules/health_dentistry/locale/uk.po
trytond/modules/health_dentistry/locale/zh_CN.po
trytond/modules/health_dentistry/pyproject.toml
trytond/modules/health_dentistry/report/__init__.py
trytond/modules/health_dentistry/report/odontogram_report.fodt
trytond/modules/health_dentistry/report/odontogram_report.py
trytond/modules/health_dentistry/report/procedures_report.fodt
trytond/modules/health_dentistry/report/procedures_report.py
trytond/modules/health_dentistry/security/access_rights.xml
trytond/modules/health_dentistry/tests/__init__.py
trytond/modules/health_dentistry/tests/test_health_dentistry.py
trytond/modules/health_dentistry/tryton.cfg
trytond/modules/health_dentistry/view/gnuhealth_dentistry_procedure_form.xml
trytond/modules/health_dentistry/view/gnuhealth_dentistry_procedure_tree.xml
trytond/modules/health_dentistry/view/gnuhealth_dentistry_treatment_form.xml
gnuhealth_dentistry-5.0.4.dist-info/METADATA
gnuhealth_dentistry-5.0.4.dist-info/WHEEL
gnuhealth_dentistry-5.0.4.dist-info/licenses/COPYING
gnuhealth_dentistry-5.0.4.dist-info/RECORD
